sentence_segmenter
